[{"map":[[1,1,1,1,1,1,1,1,1,1],[1,1,1,1,1,1,1,1,1,1],[1,1,1,1,1,1,1,1,1,1],[1,1,1,1,1,1,1,1,1,1],[1,1,1,1,1,1,1,1,1,1],[1,1,1,1,1,1,1,1,1,1],[1,1,1,1,1,1,1,1,1,1],[1,1,1,1,1,1,1,1,1,1],[1,1,1,1,1,1,1,1,1,1],[1,1,1,1,1,1,1,1,1,1],[1,1,1,1,1,1,1,1,1,1],[1,1,1,1,1,1,1,1,1,1]],"start_x":2,"limitTime":30,"id":1001,"other":[{"id":1,"y":1,"x":1},{"id":1,"y":6,"x":4},{"id":1,"y":8,"x":11}],"monster":[{"skills":[{"odds":10,"b":0,"name":"玛娜激光","cd":"5","id":2001}],"level":1,"x":2,"id":3001,"y":3,"speed":0.2,"startTime":0,"path":["2,3","3,3","4,3","5,3","6,3","7,3","8,3","9,3"],"policy":1},{"skills":[],"level":1,"x":2,"id":3001,"y":4,"speed":0.2,"startTime":5,"path":["2,4","2,5","2,6","2,7","2,8","2,9"],"policy":1},{"skills":[{"odds":10,"b":0,"name":"疯魔乱舞","cd":"5","id":1010}],"level":1,"x":2,"id":3001,"y":10,"speed":0.2,"startTime":10,"path":["2,10","3,10","4,10","5,10","6,10","7,10"],"policy":1},{"skills":[],"level":1,"x":8,"id":3001,"y":10,"speed":0.2,"startTime":20,"path":["8,10","8,9","8,8","8,7","8,6","8,5","8,4","8,3"],"policy":1},{"skills":[{"odds":10,"b":0,"name":"天崩地裂","cd":"5","id":2003},{"odds":10,"b":0,"name":"横扫重击","cd":"5","id":2008},{"odds":10,"b":0,"name":"火焰喷泉","cd":"5","id":2007}],"level":1,"x":4,"id":3011,"y":7,"speed":0.2,"startTime":30,"path":["4,7"],"policy":1}],"follower":[{"skills":[],"level":1,"x":3,"id":2004,"y":5,"startTime":5,"policy":1},{"skills":[],"level":1,"x":3,"id":2001,"y":9,"startTime":5,"policy":1},{"skills":[],"level":1,"x":7,"id":2003,"y":9,"startTime":5,"policy":1},{"skills":[],"level":1,"x":7,"id":2005,"y":5,"startTime":15,"policy":1}],"start_y":11,"start_direction":"RIGHT"},{"map":[[1,1,1,1,1,1,1,1,1,1],[1,1,1,1,1,1,1,1,1,1],[1,1,1,1,1,1,1,1,1,1],[1,1,1,1,1,1,1,1,1,1],[1,1,1,1,1,1,1,1,1,1],[1,1,1,1,1,1,1,1,1,1],[1,1,1,1,1,1,1,1,1,1],[1,1,1,1,1,1,1,1,1,1],[1,1,1,1,1,1,1,1,1,1],[1,1,1,1,1,1,1,1,1,1],[1,1,1,1,1,1,1,1,1,1],[1,1,1,1,1,1,1,1,1,1]],"start_x":2,"limitTime":60,"id":1002,"follower":[],"monster":[{"skills":[],"level":1,"x":6,"id":3007,"dropOdds":0,"y":1,"speed":0.2,"drop":0,"startTime":0,"path":["6,1"],"policy":1}],"start_y":0,"start_direction":"DOWN"}]